bank/__init__.py
bank/bank.py
bank-0.0.1.dist-info/DESCRIPTION.rst
bank-0.0.1.dist-info/METADATA
bank-0.0.1.dist-info/RECORD
bank-0.0.1.dist-info/WHEEL
bank-0.0.1.dist-info/metadata.json
bank-0.0.1.dist-info/top_level.txt
