Metadata-Version: 2.0
Name: bank
Version: 0.0.1
Summary: Core Banking for Python
Home-page: https://github.com/ourway/bank
Author: Farsheed Ashouri
Author-email: rodmena@me.com
License: Apache 2.0
Keywords: bank account core banking deposit card shop debit transfer visa express master balance
Platform: UNKNOWN
Classifier: Development Status :: 5 - Production/Stable
Classifier: Environment :: Web Environment
Classifier: Natural Language :: English
Classifier: Intended Audience :: Developers
Classifier: License :: OSI Approved :: Apache Software License
Classifier: Operating System :: MacOS :: MacOS X
Classifier: Operating System :: Microsoft :: Windows
Classifier: Operating System :: POSIX
Classifier: Topic :: Software Development :: Libraries :: Python Modules
Classifier: Programming Language :: Python
Classifier: Programming Language :: Python :: Implementation :: CPython
Classifier: Programming Language :: Python :: Implementation :: PyPy
Classifier: Programming Language :: Python :: Implementation :: Jython
Classifier: Programming Language :: Python :: 2.7
Classifier: Programming Language :: Python :: 3.5
